mo_times/__init__.py
mo_times/dates.py
mo_times/durations.py
mo_times/timer.py
mo_times-5.685.25166.dist-info/licenses/LICENSE
mo_times-5.685.25166.dist-info/METADATA
mo_times-5.685.25166.dist-info/WHEEL
mo_times-5.685.25166.dist-info/top_level.txt
mo_times-5.685.25166.dist-info/RECORD
